idact/__init__.py
idact/notebook.py
idact/core/__init__.py
idact/core/add_cluster.py
idact/core/auth.py
idact/core/cluster.py
idact/core/config.py
idact/core/dask_deployment.py
idact/core/deploy_dask.py
idact/core/environment.py
idact/core/get_default_retries.py
idact/core/jupyter_deployment.py
idact/core/node.py
idact/core/node_resource_status.py
idact/core/nodes.py
idact/core/remove_cluster.py
idact/core/retry.py
idact/core/set_log_level.py
idact/core/set_retry.py
idact/core/show_clusters.py
idact/core/synchronized_deployments.py
idact/core/tunnel.py
idact/core/walltime.py
idact/detail/__init__.py
idact/detail/cluster_impl.py
idact/detail/allocation/__init__.py
idact/detail/allocation/allocation.py
idact/detail/allocation/allocation_parameters.py
idact/detail/allocation/finalize_allocation.py
idact/detail/auth/__init__.py
idact/detail/auth/authenticate.py
idact/detail/auth/disable_getpass.py
idact/detail/auth/generate_key.py
idact/detail/auth/get_free_private_key_location.py
idact/detail/auth/get_host_string.py
idact/detail/auth/get_password.py
idact/detail/auth/get_public_key_location.py
idact/detail/auth/install_key.py
idact/detail/auth/install_shared_home_key.py
idact/detail/auth/set_password.py
idact/detail/config/__init__.py
idact/detail/config/client/__init__.py
idact/detail/config/client/client_cluster_config.py
idact/detail/config/client/client_config.py
idact/detail/config/client/client_config_serialize.py
idact/detail/config/client/retry_config_impl.py
idact/detail/config/client/retry_config_serialize.py
idact/detail/config/client/setup_actions_config.py
idact/detail/config/defaults/__init__.py
idact/detail/config/defaults/provide_defaults_for_retries.py
idact/detail/config/validation/__init__.py
idact/detail/config/validation/validate_bool.py
idact/detail/config/validation/validate_cluster_name.py
idact/detail/config/validation/validate_hostname.py
idact/detail/config/validation/validate_key_path.py
idact/detail/config/validation/validate_log_level.py
idact-0.7.dist-info/LICENSE
idact-0.7.dist-info/METADATA
idact-0.7.dist-info/WHEEL
idact-0.7.dist-info/entry_points.txt
idact-0.7.dist-info/top_level.txt
idact-0.7.dist-info/RECORD
