Metadata-Version: 2.1
Name: idact
Version: 0.7
Summary: A library that takes care of several tedious aspects of working with big data on an HPC cluster.
Home-page: https://github.com/garstka/idact
Author: Matt Garstka
Author-email: matt@garstka.net
License: MIT license
Keywords: interactive data analysis dask distributed jupyter notebook deployment slurm allocation cluster HPC ssh tunnel
Platform: UNKNOWN
Classifier: Development Status :: 4 - Beta
Classifier: License :: OSI Approved :: MIT License
Classifier: Topic :: Scientific/Engineering
Classifier: Topic :: System :: Distributed Computing
Classifier: Topic :: Utilities
Classifier: Intended Audience :: Science/Research
Classifier: Intended Audience :: Education
Classifier: Intended Audience :: Developers
Classifier: Programming Language :: Python :: 3.5
Classifier: Programming Language :: Python :: 3.6
Classifier: Operating System :: POSIX :: Linux
Classifier: Operating System :: Microsoft :: Windows
Classifier: Natural Language :: English
Requires-Dist: click (>=6.7)
Requires-Dist: fabric3 (>=1.14)
Requires-Dist: bitmath (>=1.3.1.2)
Requires-Dist: python-dateutil (>=2.7.2)
Requires-Dist: sshtunnel (>=0.1.4)
Requires-Dist: paramiko (>=2.4.1)
Requires-Dist: dask (>=0.18.2)
Requires-Dist: distributed (>=1.22.0)
Requires-Dist: requests (>=2.18.4)
Requires-Dist: bokeh (>=0.13.0)
Requires-Dist: jupyter (>=1.0.0)
Requires-Dist: jupyterlab (>=0.35.4)
